ipgelo/__init__.py
ipgelo-0.1.0.dist-info/METADATA
ipgelo-0.1.0.dist-info/WHEEL
ipgelo-0.1.0.dist-info/top_level.txt
ipgelo-0.1.0.dist-info/RECORD
