Metadata-Version: 2.4
Name: ipgelo
Version: 0.1.0
Summary: A Python module that can get geolocation data from an IP Address.
Author: cocoa
Classifier: Programming Language :: Python :: 3
Classifier: Operating System :: OS Independent
Requires-Python: >=3.7
Requires-Dist: requests
Dynamic: author
Dynamic: classifier
Dynamic: description
Dynamic: description-content-type
Dynamic: requires-dist
Dynamic: requires-python
Dynamic: summary
